setup.py
tinkerforge/__init__.py
tinkerforge/brick_dc.py
tinkerforge/brick_esp32.py
tinkerforge/brick_esp32_ethernet.py
tinkerforge/brick_hat.py
tinkerforge/brick_hat_zero.py
tinkerforge/brick_imu.py
tinkerforge/brick_imu_v2.py
tinkerforge/brick_master.py
tinkerforge/brick_red.py
tinkerforge/brick_servo.py
tinkerforge/brick_silent_stepper.py
tinkerforge/brick_stepper.py
tinkerforge/bricklet_accelerometer.py
tinkerforge/bricklet_accelerometer_v2.py
tinkerforge/bricklet_air_quality.py
tinkerforge/bricklet_ambient_light.py
tinkerforge/bricklet_ambient_light_v2.py
tinkerforge/bricklet_ambient_light_v3.py
tinkerforge/bricklet_analog_in.py
tinkerforge/bricklet_analog_in_v2.py
tinkerforge/bricklet_analog_in_v3.py
tinkerforge/bricklet_analog_out.py
tinkerforge/bricklet_analog_out_v2.py
tinkerforge/bricklet_analog_out_v3.py
tinkerforge/bricklet_barometer.py
tinkerforge/bricklet_barometer_v2.py
tinkerforge/bricklet_can.py
tinkerforge/bricklet_can_v2.py
tinkerforge/bricklet_co2.py
tinkerforge/bricklet_co2_v2.py
tinkerforge/bricklet_color.py
tinkerforge/bricklet_color_v2.py
tinkerforge/bricklet_compass.py
tinkerforge/bricklet_current12.py
tinkerforge/bricklet_current25.py
tinkerforge/bricklet_dc_v2.py
tinkerforge/bricklet_distance_ir.py
tinkerforge/bricklet_distance_ir_v2.py
tinkerforge/bricklet_distance_us.py
tinkerforge/bricklet_distance_us_v2.py
tinkerforge/bricklet_dmx.py
tinkerforge/bricklet_dual_button.py
tinkerforge/bricklet_dual_button_v2.py
tinkerforge/bricklet_dual_relay.py
tinkerforge/bricklet_dust_detector.py
tinkerforge/bricklet_e_paper_296x128.py
tinkerforge/bricklet_energy_monitor.py
tinkerforge/bricklet_gps.py
tinkerforge/bricklet_gps_v2.py
tinkerforge/bricklet_gps_v3.py
tinkerforge/bricklet_hall_effect.py
tinkerforge/bricklet_hall_effect_v2.py
tinkerforge/bricklet_humidity.py
tinkerforge/bricklet_humidity_v2.py
tinkerforge/bricklet_imu_v3.py
tinkerforge/bricklet_industrial_analog_out.py
tinkerforge/bricklet_industrial_analog_out_v2.py
tinkerforge.egg-info/PKG-INFO
tinkerforge.egg-info/SOURCES.txt
tinkerforge.egg-info/dependency_links.txt
tinkerforge.egg-info/top_level.txt