Metadata-Version: 2.1
Name: tinkerforge
Version: 2.1.32
Summary: Python API Bindings for Tinkerforge Bricks and Bricklets
Home-page: https://www.tinkerforge.com
Author: Tinkerforge GmbH
Author-email: olaf@tinkerforge.com
License: CC0 1.0 Universal
Platform: Any
